gym_jsbsim/__init__.py
gym_jsbsim/jsbsim_env.py
gym_jsbsim/simulation.py
gym_jsbsim/task.py
gym_jsbsim/version.py
gym_jsbsim/catalogs/__init__.py
gym_jsbsim/catalogs/catalog.py
gym_jsbsim/catalogs/jsbsim_catalog.py
gym_jsbsim/catalogs/my_catalog.py
gym_jsbsim/catalogs/property.py
gym_jsbsim/catalogs/utils.py
gym_jsbsim/envs/__init__.py
gym_jsbsim/envs/approach_control_task.py
gym_jsbsim/envs/heading_altitude_control_task.py
gym_jsbsim/envs/heading_control_task.py
gym_jsbsim/envs/taxi_control_task.py
gym_jsbsim/envs/taxi_utils.py
gym_jsbsim/envs/taxiap_control_task.py
gym_jsbsim/jsbsim-1.1.1/aircraft/737/737.xml
gym_jsbsim/jsbsim-1.1.1/aircraft/737/cruise_init.xml
gym_jsbsim/jsbsim-1.1.1/aircraft/737/cruise_steady_turn_init.xml
gym_jsbsim/jsbsim-1.1.1/aircraft/737/reset00.xml
gym_jsbsim/jsbsim-1.1.1/aircraft/A320/A320.xml
gym_jsbsim/jsbsim-1.1.1/aircraft/A320/A320ap.xml
gym_jsbsim/jsbsim-1.1.1/aircraft/A4/A4.xml
gym_jsbsim/jsbsim-1.1.1/aircraft/B17/B17.xml
gym_jsbsim/jsbsim-1.1.1/aircraft/B17/reset00.xml
gym_jsbsim/jsbsim-1.1.1/aircraft/B747/B747.xml
gym_jsbsim/jsbsim-1.1.1/aircraft/B747/reset00.xml
gym_jsbsim/jsbsim-1.1.1/aircraft/Boeing314/Boeing314.xml
gym_jsbsim/jsbsim-1.1.1/aircraft/C130/C130.xml
gym_jsbsim/jsbsim-1.1.1/aircraft/C130/reset00.xml
gym_jsbsim/jsbsim-1.1.1/aircraft/Camel/sopwithCamel1F1jsb.xml
gym_jsbsim/jsbsim-1.1.1/aircraft/Concorde/Concorde.xml
gym_jsbsim/jsbsim-1.1.1/aircraft/Concorde/reset00.xml
gym_jsbsim/jsbsim-1.1.1/aircraft/DHC6/DHC6.xml
gym_jsbsim/jsbsim-1.1.1/aircraft/F4N/F4N-jsbsim.xml
gym_jsbsim/jsbsim-1.1.1/aircraft/F4N/F4N.xml
gym_jsbsim/jsbsim-1.1.1/aircraft/F4N/reset00.xml
gym_jsbsim/jsbsim-1.1.1/aircraft/F80C/F80C.xml
gym_jsbsim/jsbsim-1.1.1/aircraft/J246/J246.xml
gym_jsbsim/jsbsim-1.1.1/aircraft/J246/LC39.xml
gym_jsbsim/jsbsim-1.1.1/aircraft/J3Cub/J3Cub.xml
gym_jsbsim/jsbsim-1.1.1/aircraft/L17/L17.xml
gym_jsbsim/jsbsim-1.1.1/aircraft/L410/L410.xml
gym_jsbsim/jsbsim-1.1.1/aircraft/L410/reset00.xml
gym_jsbsim-0.6.7.dist-info/LICENSE
gym_jsbsim-0.6.7.dist-info/METADATA
gym_jsbsim-0.6.7.dist-info/WHEEL
gym_jsbsim-0.6.7.dist-info/top_level.txt
gym_jsbsim-0.6.7.dist-info/RECORD
