Metadata-Version: 2.1
Name: gym-jsbsim
Version: 0.6.7
Summary: Gym JSBSim environment
Home-page: https://github.com/galleon/gym-jsbsim
Author: Guillaume Alleon
Author-email: guillaume.alleon@gmail.com
License: LGPL 2.1
Platform: UNKNOWN
Classifier: Intended Audience :: Developers
Classifier: Intended Audience :: Education
Classifier: Intended Audience :: Science/Research
Classifier: Operating System :: POSIX :: Linux
Classifier: Programming Language :: Python :: 3 :: Only
Classifier: License :: OSI Approved :: MIT License
Classifier: Topic :: Scientific/Engineering :: Artificial Intelligence
Classifier: Topic :: Games/Entertainment :: Simulation
Classifier: Topic :: Software Development :: Libraries
Requires-Python: >3.6
Requires-Dist: jsbsim (>=1.1.1)
Requires-Dist: folium (>=0.10.1)
Requires-Dist: geographiclib (>=1.50)
Requires-Dist: gym (>=0.15.7)
Requires-Dist: shapely (>=1.7.1)
